creed_guardian/__init__.py
creed_guardian/client.py
creed_guardian/exceptions.py
creed_guardian/guardian.py
creed_guardian/types.py
creed_guardian/tests/__init__.py
creed_guardian/tests/test_guardian.py
creed_guardian-0.1.0.dist-info/licenses/LICENSE
creed_guardian-0.1.0.dist-info/METADATA
creed_guardian-0.1.0.dist-info/WHEEL
creed_guardian-0.1.0.dist-info/top_level.txt
creed_guardian-0.1.0.dist-info/RECORD
