Metadata-Version: 2.4
Name: creed-guardian
Version: 0.1.0
Summary: Local AI safety for any device. Free forever.
Author-email: Creed Space <hello@creed.space>
License: MIT
Project-URL: Homepage, https://creed.space/guardian
Project-URL: Documentation, https://creed.space/docs/guardian
Project-URL: Repository, https://github.com/Creed-Space/guardian
Project-URL: Issues, https://github.com/Creed-Space/guardian/issues
Keywords: ai,safety,constitutional,llm,guardian,ollama,agentic
Classifier: Development Status :: 4 - Beta
Classifier: Intended Audience :: Developers
Classifier: License :: OSI Approved :: MIT License
Classifier: Operating System :: OS Independent
Classifier: Programming Language :: Python :: 3
Classifier: Programming Language :: Python :: 3.9
Classifier: Programming Language :: Python :: 3.10
Classifier: Programming Language :: Python :: 3.11
Classifier: Programming Language :: Python :: 3.12
Classifier: Topic :: Scientific/Engineering :: Artificial Intelligence
Classifier: Topic :: Security
Requires-Python: >=3.9
License-File: LICENSE
Requires-Dist: httpx>=0.24.0
Requires-Dist: psutil>=5.9.0
Provides-Extra: dev
Requires-Dist: pytest>=7.0.0; extra == "dev"
Requires-Dist: pytest-asyncio>=0.21.0; extra == "dev"
Requires-Dist: pytest-cov>=4.0.0; extra == "dev"
Requires-Dist: black>=23.0.0; extra == "dev"
Requires-Dist: ruff>=0.1.0; extra == "dev"
Requires-Dist: mypy>=1.0.0; extra == "dev"
Dynamic: license-file
